{"cameraMode":{"drawMode":0,"name":"Shaded","section":"Shading Mode"},"sceneLighting":false,"audioPlay":false,"sceneViewState":{"m_AlwaysRefresh":false,"showFog":true,"showSkybox":true,"showFlares":true,"showImageEffects":true,"showParticleSystems":true,"showVisualEffectGraphs":true,"m_FxEnabled":true},"in2DMode":false,"pivot":{"x":288.029296875,"y":220.50909423828126,"z":20.85968017578125},"rotation":{"x":0.016801897436380388,"y":-0.012913034297525883,"z":-0.0002055946533801034,"w":-0.9998913407325745},"size":193.6578369140625,"orthographic":false}